unbored/__init__.py
unbored/__main__.py
unbored/activity.py
unbored/app.py
unbored/filter_input.py
unbored/filters.py
unbored/focus_within.py
unbored/main_screen.py
unbored/py.typed
unbored/type_choices.py
unbored/unbored.css
unbored-0.6.0.dist-info/LICENSE
unbored-0.6.0.dist-info/METADATA
unbored-0.6.0.dist-info/WHEEL
unbored-0.6.0.dist-info/entry_points.txt
unbored-0.6.0.dist-info/top_level.txt
unbored-0.6.0.dist-info/RECORD
